README.md
setup.py
dc_electricity.egg-info/PKG-INFO
dc_electricity.egg-info/SOURCES.txt
dc_electricity.egg-info/dependency_links.txt
dc_electricity.egg-info/top_level.txt
dcelectricity/__init__.py
dcelectricity/dc_en.py
dcelectricity/dc_fr.py