Metadata-Version: 2.1
Name: dc-electricity
Version: 0.2.6
Summary: An educational package about linear DC electrical circuits
Home-page: http://fsincere.free.fr/isn/python/cours_python_dc.php
Author: Fabrice Sincère
Author-email: fabrice.sincere@ac-grenoble.fr
Maintainer: Fabrice Sincère
Maintainer-email: fabrice.sincere@ac-grenoble.fr
License: UNKNOWN
Platform: UNKNOWN
Classifier: Programming Language :: Python :: 3
Classifier: Intended Audience :: Education
Classifier: Intended Audience :: Science/Research
Classifier: Topic :: Scientific/Engineering :: Physics
Classifier: License :: OSI Approved :: GNU General Public License v3 (GPLv3)
Classifier: Operating System :: OS Independent
Requires-Python: >=3
